xchainpy2_arbitrum/__init__.py
xchainpy2_arbitrum/arb_client.py
xchainpy2_arbitrum/consts.py
xchainpy2_arbitrum/data/arb_mainnet_latest.json
xchainpy2_arbitrum-0.0.5.dist-info/licenses/LICENSE
xchainpy2_arbitrum-0.0.5.dist-info/METADATA
xchainpy2_arbitrum-0.0.5.dist-info/WHEEL
xchainpy2_arbitrum-0.0.5.dist-info/top_level.txt
xchainpy2_arbitrum-0.0.5.dist-info/RECORD
